json_excel_converter/__init__.py
json_excel_converter/converter.py
json_excel_converter/csv/__init__.py
json_excel_converter/linearize.py
json_excel_converter/options.py
json_excel_converter/xlsx/__init__.py
json_excel_converter/xlsx/formats.py
poetry.lock
json_excel_converter-1.3.0.dist-info/entry_points.txt
json_excel_converter-1.3.0.dist-info/LICENSE
json_excel_converter-1.3.0.dist-info/WHEEL
json_excel_converter-1.3.0.dist-info/METADATA
json_excel_converter-1.3.0.dist-info/RECORD
