Metadata-Version: 2.1
Name: json-excel-converter
Version: 1.3.0
Summary: JSON to excel convertor
Home-page: https://github.com/oarepo/json-excel-converter
Keywords: json,excel,csv,xlsxwriter
Author: Mirek Simek
Author-email: miroslav.simek@vscht.cz
Requires-Python: >=3.6,<4.0
Classifier: Development Status :: 4 - Beta
Classifier: Programming Language :: Python :: 3
Classifier: Programming Language :: Python :: 3.6
Classifier: Programming Language :: Python :: 3.7
Classifier: Programming Language :: Python :: 3.8
Classifier: Topic :: Software Development :: Libraries :: Python Modules
Provides-Extra: xlsxwriter
Requires-Dist: xlsxwriter (>=1.2,<2.0); extra == "xlsxwriter"
Project-URL: Repository, https://github.com/oarepo/json-excel-converter
